dirty_bits.py
setup.py
django_dirty_bits.egg-info/PKG-INFO
django_dirty_bits.egg-info/SOURCES.txt
django_dirty_bits.egg-info/dependency_links.txt
django_dirty_bits.egg-info/requires.txt
django_dirty_bits.egg-info/top_level.txt