Metadata-Version: 1.0
Name: django-dirty-bits
Version: 0.1.3
Summary: Dirty bits checking for Django models
Home-page: UNKNOWN
Author: Michael Milkin
Author-email: mmilkin@gmail.com
License: UNKNOWN
Platform: UNKNOWN
